MAMMAL/__init__.py
MAMMAL/Diurnal/__init__.py
MAMMAL/MapLvl/__init__.py
MAMMAL/MapLvl/pcaLvl.py
MAMMAL/MapLvl/tieLvl.py
MAMMAL/Parse/__init__.py
MAMMAL/Parse/parseGSMP.py
MAMMAL/Parse/parseGeometrics.py
MAMMAL/Parse/parseIM.py
MAMMAL/Parse/parsePixhawk.py
MAMMAL/Parse/parseRaster.py
MAMMAL/Parse/parseSGL.py
MAMMAL/SensorCal/__init__.py
MAMMAL/SensorCal/spinCal.py
MAMMAL/Simulator/__init__.py
MAMMAL/Utils/Filters.py
MAMMAL/Utils/ProcessingUtils.py
MAMMAL/Utils/__init__.py
MAMMAL/Utils/coordinateUtils.py
MAMMAL/Utils/mapUtils.py
MAMMAL/VehicleCal/TL.py
MAMMAL/VehicleCal/__init__.py
MAMMAL/VehicleCal/magUtilsTL.py
MAMMAL_MagNav-0.0.1.dist-info/METADATA
MAMMAL_MagNav-0.0.1.dist-info/WHEEL
MAMMAL_MagNav-0.0.1.dist-info/top_level.txt
MAMMAL_MagNav-0.0.1.dist-info/RECORD
