Metadata-Version: 2.1
Name: MAMMAL-MagNav
Version: 0.0.1
Summary: Python package used to create aeromagnetic anomaly maps for Magnetic Navigation (MagNav)
Home-page: https://github.com/PowerBroker2/MAMMAL
Download-URL: https://github.com/PowerBroker2/MAMMAL/archive/0.0.1.tar.gz
Author: Power_Broker
Author-email: gitstuff2@gmail.com
Keywords: navigation,mapping,geospatial,magnetometer,survey,remote-sensing,magnet,magnav
Requires-Dist: numpy (==1.20.3)
Requires-Dist: pandas (==1.3.4)
Requires-Dist: scipy (==1.7.1)
Requires-Dist: matplotlib (==3.4.3)
Requires-Dist: tqdm (==4.62.3)
Requires-Dist: xarray (==2022.3.0)
Requires-Dist: rioxarray (==0.10.3)
Requires-Dist: scikit-learn (==0.24.2)
Requires-Dist: ppigrf (==1.0.0)
Requires-Dist: geoscraper (==0.0.1)
Requires-Dist: simplekml (==1.3.3)
